Adifpy/__init__.py
Adifpy/differentiate/dual_number.py
Adifpy/differentiate/evaluator.py
Adifpy/differentiate/forward_mode.py
Adifpy/differentiate/helpers.py
Adifpy/differentiate/node.py
Adifpy/differentiate/reverse_mode.py
Adifpy/test/.bash_history
Adifpy/test/.coverage
Adifpy/test/README.md
Adifpy/test/run_tests.sh
Adifpy/test/test_dual_number.py
Adifpy/test/test_evaluator.py
Adifpy/test/test_forward_mode.py
Adifpy/test/test_graph_function.py
Adifpy/test/test_reverse_mode.py
Adifpy/test/.pytest_cache/.gitignore
Adifpy/test/.pytest_cache/CACHEDIR.TAG
Adifpy/test/.pytest_cache/README.md
Adifpy/test/.pytest_cache/v/cache/lastfailed
Adifpy/test/.pytest_cache/v/cache/nodeids
Adifpy/test/.pytest_cache/v/cache/stepwise
Adifpy/test/tests/htmlcov/.gitignore
Adifpy/test/tests/htmlcov/coverage_html.js
Adifpy/test/tests/htmlcov/d_0b83692be68a45f5_graph_function_py.html
Adifpy/test/tests/htmlcov/d_125b0591291dc932___init___py.html
Adifpy/test/tests/htmlcov/d_deb447b67093d5d9_dual_number_py.html
Adifpy/test/tests/htmlcov/d_deb447b67093d5d9_evaluator_py.html
Adifpy/test/tests/htmlcov/d_deb447b67093d5d9_forward_mode_py.html
Adifpy/test/tests/htmlcov/d_deb447b67093d5d9_helpers_py.html
Adifpy/test/tests/htmlcov/d_deb447b67093d5d9_node_py.html
Adifpy/test/tests/htmlcov/d_deb447b67093d5d9_reverse_mode_py.html
Adifpy/test/tests/htmlcov/favicon_32.png
Adifpy/test/tests/htmlcov/index.html
Adifpy/test/tests/htmlcov/keybd_closed.png
Adifpy/test/tests/htmlcov/keybd_open.png
Adifpy/test/tests/htmlcov/status.json
Adifpy/test/tests/htmlcov/style.css
Adifpy/visualize/graph_function.py
Adifpy/visualize/img.png
adifpy-0.0.3.dist-info/METADATA
adifpy-0.0.3.dist-info/WHEEL
adifpy-0.0.3.dist-info/licenses/LICENSE
adifpy-0.0.3.dist-info/RECORD
