Metadata-Version: 2.1
Name: Adifpy
Version: 0.0.3
Summary: Perform automatic differentiation
Project-URL: Homepage, https://code.harvard.edu/CS107/team33
Author-email: Aaron Berger <aaronberger@college.harvard.edu>, Alex Tonelli <atonelli@college.harvard.edu>, Eli Kirtley <elikirtley@college.harvard.edu>, Jack Tian <jtian@college.harvard.eduu>, Ream Gebrekidan <rgebrekidan@college.harvard.edu>
License-File: LICENSE
Classifier: License :: OSI Approved :: MIT License
Classifier: Operating System :: OS Independent
Classifier: Programming Language :: Python :: 3
Requires-Python: >=3.10
Requires-Dist: matplotlib~=3.6.1
Requires-Dist: numpy~=1.23.4
